# 泛型

一般的类和方法, 只能使用具体的类型: 要么是基本类型, 要么是自定义的类.
如果要编写可以应用于多种类型的代码, 这种刻板的限制对代码的束缚就会很大.

在面向对象编程语言中, 多态算是一种泛化机制
例如:你可以将方法的参数类型设置为基类,
那么这个方法就可以接受任何从这个基类导出的子类作为参数.
这样的方法应用的范围更加广一些,更加通用一些.

在单继承结构中, 有时用基类作为参数类型还是会让程序有太多限制.
如果方法参数是一个接口, 而不是类那么这种限制就放松了许多, 因为任何实现了该接口的类都能够满足该方法.

可有时即使使用了接口, 对程序的约束还是太强了.
因为一旦指明了接口, 它就要求你的代码必须使用特定接口.
而我们想编写的更通用的代码, 不限制类型的方法, 而不是一个具体的类或接口

于是在 Java SE5 中添加了 泛型的概念

泛型实现了 **参数化类型** 的概念,使代码可以用于多种类型
> 泛型在编程语言中出现时, 其最初的目的时希望类或方法能够具备最广泛的表达能力.
>
> 如何做到这一点呢, 正是通过解耦类或方法于使用的类型之间的约束

当然 Java 中的泛型没有这么高的追求, 换句话说 Java 中的 泛型并不完整

# 简单泛型

# 泛型接口

# 泛型方法

## Java泛型的缺点

泛型的确定是由于实现方式 是 **擦除** 这是一种折中的方案

* 基本类型不能作为参数类型
  public class com.wkunc.injava.generic.SimpleHolder {
  public com.wkunc.injava.generic.SimpleHolder();
  Code:
  0: aload_0
  1: invokespecial #1 // Method java/lang/Object."<init>":()V
  4: return

  public java.lang.Object get();
  Code:
  0: aload_0
  1: getfield #2 // Field obj:Ljava/lang/Object;
  4: areturn

  public void set(java.lang.Object);
  Code:
  0: aload_0
  1: aload_1
  2: putfield #2 // Field obj:Ljava/lang/Object;
  5: return

  public static void main(java.lang.String[]);
  Code:
  0: new #3 // class com/wkunc/injava/generic/SimpleHolder
  3: dup
  4: invokespecial #4 // Method "<init>":()V
  7: astore_1
  8: aload_1
  9: ldc #5 // String item
  11: invokevirtual #6 // Method set:(Ljava/lang/Object;)V
  14: aload_1
  15: invokevirtual #7 // Method get:()Ljava/lang/Object;
  18: checkcast #8 // class java/lang/String
  21: astore_2
  22: return
  }
  public class com.wkunc.injava.generic.GenericHolder<T> {
  public com.wkunc.injava.generic.GenericHolder();
  Code:
  0: aload_0
  1: invokespecial #1 // Method java/lang/Object."<init>":()V
  4: return

  public T get();
  Code:
  0: aload_0
  1: getfield #2 // Field obj:Ljava/lang/Object;
  4: areturn

  public void set(T);
  Code:
  0: aload_0
  1: aload_1
  2: putfield #2 // Field obj:Ljava/lang/Object;
  5: return

  public static void main(java.lang.String[]);
  Code:
  0: new #3 // class com/wkunc/injava/generic/GenericHolder
  3: dup
  4: invokespecial #4 // Method "<init>":()V
  7: astore_1
  8: aload_1
  9: ldc #5 // String item
  11: invokevirtual #6 // Method set:(Ljava/lang/Object;)V
  14: aload_1
  15: invokevirtual #7 // Method get:()Ljava/lang/Object;
  18: checkcast #8 // class java/lang/String
  21: astore_2
  22: return
  }


